CHANGELOG.md
LICENSE
MANIFEST.in
README.md
requirements.txt
setup.py
bin/cihpc
bin/cihpc-www
cihpc/__init__.py
cihpc/_version.py
cihpc.egg-info/PKG-INFO
cihpc.egg-info/SOURCES.txt
cihpc.egg-info/dependency_links.txt
cihpc.egg-info/requires.txt
cihpc.egg-info/top_level.txt
cihpc/artifacts/__init__.py
cihpc/artifacts/modules/__init__.py
cihpc/artifacts/modules/fenics_module.py
cihpc/artifacts/modules/flow123d_profiler.py
cihpc/artifacts/modules/flow123d_profiler_module.py
cihpc/artifacts/modules/generic_module.py
cihpc/cfg/__init__.py
cihpc/cfg/cfgutil.py
cihpc/cfg/config.py
cihpc/common/__init__.py
cihpc/common/logging/__init__.py
cihpc/common/logging/formatters.py
cihpc/common/processing/__init__.py
cihpc/common/processing/multiprocessing_pool.py
cihpc/common/processing/pool.py
cihpc/common/processing/daemon/__init__.py
cihpc/common/utils/__init__.py
cihpc/common/utils/colors.py
cihpc/common/utils/datautils.py
cihpc/common/utils/dateutils.py
cihpc/common/utils/events.py
cihpc/common/utils/extend_yaml.py
cihpc/common/utils/html_argparse.py
cihpc/common/utils/parallels.py
cihpc/common/utils/parsing.py
cihpc/common/utils/strings.py
cihpc/common/utils/timer.py
cihpc/common/utils/caching/__init__.py
cihpc/common/utils/files/__init__.py
cihpc/common/utils/files/dynamic_io.py
cihpc/common/utils/files/temp_file.py
cihpc/common/utils/git/__init__.py
cihpc/common/utils/git/webhooks/__init__.py
cihpc/common/utils/git/webhooks/push_hook/__init__.py
cihpc/core/__init__.py
cihpc/core/db/__init__.py
cihpc/core/execution/__init__.py
cihpc/core/processing/__init__.py
cihpc/core/processing/project.py
cihpc/core/processing/step_collect.py
cihpc/core/processing/step_collect_parse.py
cihpc/core/processing/step_git.py
cihpc/core/processing/step_measure.py
cihpc/core/processing/step_shell.py
cihpc/core/structures/__init__.py
cihpc/core/structures/project.py
cihpc/core/structures/project_section.py
cihpc/core/structures/project_step.py
cihpc/core/structures/project_step_collect.py
cihpc/core/structures/project_step_collect_parse.py
cihpc/core/structures/project_step_container.py
cihpc/core/structures/project_step_git.py
